easy_tasks/__init__.py
easy_tasks/closest_furthest_value.py
easy_tasks/dublicates.py
easy_tasks/filesystem.py
easy_tasks/help_with_json.py
easy_tasks/help_with_pickle.py
easy_tasks/list_printer.py
easy_tasks/percentage.py
easy_tasks/rounding.py
easy_tasks/sorter.py
easy_tasks/stoppable_thread.py
easy_tasks/string_transformation.py
easy_tasks/types.py
easy_tasks/unpack.py
easy_tasks/zipping.py
easy_tasks-0.0.55.dist-info/licenses/LICENSE
easy_tasks-0.0.55.dist-info/METADATA
easy_tasks-0.0.55.dist-info/WHEEL
easy_tasks-0.0.55.dist-info/top_level.txt
easy_tasks-0.0.55.dist-info/RECORD
