Metadata-Version: 2.4
Name: easy_tasks
Version: 0.0.55
Summary: Normal python class tasks like sorting, closet/furthest value, dublicates, ...
Author: André Herber
Author-email: andre.herber.programming@gmail.com
Keywords: python
Classifier: Development Status :: 1 - Planning
Classifier: Intended Audience :: Developers
Classifier: Programming Language :: Python :: 3
Classifier: Programming Language :: Python :: 3.9
Classifier: Programming Language :: Python :: 3.10
Classifier: License :: OSI Approved :: MIT License
Classifier: Operating System :: Microsoft :: Windows
License-File: LICENSE
Requires-Dist: colorful_terminal
Requires-Dist: exception_details
Requires-Dist: natsort
Requires-Dist: var_print
Requires-Dist: pywin32
Requires-Dist: clipboard
Requires-Dist: executing
Requires-Dist: know_the_time
Dynamic: author
Dynamic: author-email
Dynamic: classifier
Dynamic: description
Dynamic: description-content-type
Dynamic: keywords
Dynamic: license-file
Dynamic: requires-dist
Dynamic: summary
